cs233/exam/exam1/p1/circuit.v
// Netflix has been engaged by movie studios to advertise new movies.
// Netflix will show visitors one of 4 ads based on the kind of movie
// they last watched.

// The following characteristics of the last watched movie are
// considered:
// - Whether the movie was animated? (A = 1 means the movie was
//     animated; otherwise A = 0)
// - Whether the starring actor was female (F = 1) or male (F = 0)?
// - The type of movie: (T = 2'b00 (action movie), 2'b01 (romance),
//     2'b10 (comedy), 2'b11 (thriller))

// The ad served is chosen by the following rules:
// - "A Good Day to Die Hard" (M = 2'b00) will be shown to viewers of
//     action movies and thrillers, unless they are animated or had a
//     female starring actor.
// - "Safe Haven" (M = 2'b01) will be selected for people who had
//     viewed romance movies or movies with a female starring actor that
//     are not comedies.
// - When the previous two movie ads aren't shown, "Escape from Planet
//     Earth" (M = 2'b10) will be shown to people viewing animated movies,
//     comedies, or action movies.
// - Otherwise, "Saving Lincoln" (M = 2'b11) will be shown.

module movies(M, A, F, T);
   output [1:0] M;
   input  	A, F;
   input  [1:0]	T;
   wire m1,m2,m3,m4,w1,w2,w3,w4,w5,w6,w7,t1,t2,t3,t4;

   or o1(w1,t1,t4);
   nor no1(w2,A,F);
   and a1(m1,w1,w2);
   or o2(w4,t2,F);
   not n1(w3,t3);
   and a2(m2,w4,w3);

   not n2(w5,m1);
   not n3(w6,m2);
   or o3(w7,A,t3,t1);
   and a3(m3,w5,w6,w7);

   nor no2(m4,m3,m2,m1);

   assign t1 = T[1:0]==2'b00;
   assign t2 = T[1:0]==2'b01;
   assign t3 = T[1:0]==2'b10;
   assign t4 = T[1:0]==2'b11;

   assign M[0] = m2|m4;
   assign M[1] = m3|m4;


endmodule // movies

cs233/exam/exam1/p1/circuit_tb.v
module test;

   // these are inputs to "circuit under test"
   reg       A;
   reg       F;
   reg [1:0] T;
   
  // wires for the outputs of "circuit under test"
   wire [1:0] M;
  // the circuit under test
   movies m(M, A, F, T);  
    
   initial begin               // initial = run at beginning of simulation
                               // begin/end = associate block with initial
      
      $dumpfile("test.vcd");  // name of dump file to create
      $dumpvars(0, test);     // record all signals of module "test" and sub-modules
                              // remember to change "test" to the correct
                              // module name when writing your own test benches
        
      // test all input combinations
      A = 0; F = 0; T = 0; #10;
      A = 0; F = 0; T = 1; #10;
      A = 0; F = 0; T = 2; #10;
      A = 0; F = 0; T = 3; #10;
      A = 0; F = 1; T = 0; #10;
      A = 0; F = 1; T = 1; #10;
      A = 0; F = 1; T = 2; #10;
      A = 0; F = 1; T = 3; #10;
      A = 1; F = 0; T = 0; #10;
      A = 1; F = 0; T = 1; #10;
      A = 1; F = 0; T = 2; #10;
      A = 1; F = 0; T = 3; #10;
      A = 1; F = 1; T = 0; #10;
      A = 1; F = 1; T = 1; #10;
      A = 1; F = 1; T = 2; #10;
      A = 1; F = 1; T = 3; #10;
      
      $finish;        // end the simulation
   end                      
   
   initial begin
     $display("inputs = A, F, T   outputs = M");
     $monitor("inputs = %b  %b  %b  outputs = %b   time = %2t",
              A, F, T, M, $time);
   end
endmodule // test

cs233/exam/exam1/p1/test.vcd
$date
	Tue Feb  6 14:54:17 2018
$end
$version
	Icarus Verilog
$end
$timescale
	1s
$end
$scope module test $end
$var wire 2 ! M [1:0] $end
$var reg 1 " A $end
$var reg 1 # F $end
$var reg 2 $ T [1:0] $end
$scope module m $end
$var wire 1 " A $end
$var wire 1 # F $end
$var wire 2 % T [1:0] $end
$var wire 1 & m1 $end
$var wire 1 ' m2 $end
$var wire 1 ( m3 $end
$var wire 1 ) m4 $end
$var wire 1 * w1 $end
$var wire 1 + w2 $end
$var wire 1 , w3 $end
$var wire 1 - w4 $end
$var wire 1 . w5 $end
$var wire 1 / w6 $end
$var wire 1 0 w7 $end
$var wire 1 1 t4 $end
$var wire 1 2 t3 $end
$var wire 1 3 t2 $end
$var wire 1 4 t1 $end
$var wire 2 5 M [1:0] $end
$upscope $end
$upscope $end
$enddefinitions $end
#0
$dumpvars
b0 5
14
03
02
01
10
1/
0.
0-
1,
1+
1*
0)
0(
0'
1&
b0 %
b0 $
0#
0"
b0 !
$end
#10
1.
0/
b1 !
b1 5
0&
1'
00
0*
1-
04
13
b1 $
b1 %
#20
1(
1/
0)
b10 !
b10 5
0'
0-
10
0,
03
12
b10 $
b10 %
#30
b0 !
b0 5
0.
0(
1&
00
1,
1*
02
11
b11 $
b11 %
#40
1.
0/
b1 !
b1 5
0&
1'
10
0+
1-
14
01
b0 $
b0 %
1#
#50
00
0*
04
13
b1 $
b1 %
#60
1(
1/
0)
b10 !
b10 5
0'
10
0,
03
12
b10 $
b10 %
#70
0/
b1 !
b1 5
0(
1'
00
1,
1*
02
11
b11 $
b11 %
#80
1(
1/
0)
b10 !
b10 5
0'
0-
10
14
01
b0 $
b0 %
0#
1"
#90
0(
0/
b1 !
b1 5
1'
0*
1-
04
13
b1 $
b1 %
#100
1(
1/
0)
b10 !
b10 5
0'
0-
0,
03
12
b10 $
b10 %
#110
1,
1*
02
11
b11 $
b11 %
#120
0(
0/
b1 !
b1 5
1'
1-
14
01
b0 $
b0 %
1#
#130
0*
04
13
b1 $
b1 %
#140
1(
1/
0)
b10 !
b10 5
0'
0,
03
12
b10 $
b10 %
#150
0(
0/
b1 !
b1 5
1'
1,
1*
02
11
b11 $
b11 %
