cs233/exam/exam1/p2/circuit.v
// Design a circuit that divides a 4-bit signed binary number (in)
// by 3 to produce a 3-bit signed binary number (out).  Note that
// integer division rounds toward zero for both positive and negative
// numbers (e.g., -5/3 is -1).

module sdiv3(out, in);
   output [2:0] out;
   input  [3:0]	in;

//   assign out[2] = (in[3]==1)& ~( ~(in[2]^in[1])& (in[2]&in[1]));
//   assign out[1] = ((in[3]==1)& ~( ~(in[2]^in[1])& (in[2]&in[1])) ) | ((in[3]==0)& ~(in[2]^in[1])) ;
   assign out[0] = (in[3:0]== 4'b1011)|(in[3:0]== 4'b1100)|(in[3:0]== 4'b1101)|(in[3:0]== 4'b0011)|(in[3:0]== 4'b0100)|(in[3:0]== 4'b0101);
   assign out[1] = (in[3:0]== 4'b1011)|(in[3:0]== 4'b1100)|(in[3:0]== 4'b1101)|(in[3:0]== 4'b1000)|(in[3:0]== 4'b1001)|(in[3:0]== 4'b1010)|(in[3:0]== 4'b0110)|(in[3:0]== 4'b0111);
   assign out[2] = (in[3:0]== 4'b1011)|(in[3:0]== 4'b1100)|(in[3:0]== 4'b1101)|(in[3:0]== 4'b1000)|(in[3:0]== 4'b1001)|(in[3:0]== 4'b1010);

endmodule // sdiv3

cs233/exam/exam1/p2/circuit_tb.v
module test;

   // these are inputs to "circuit under test"
   reg signed [3:0] in;

  // wires for the outputs of "circuit under test"
   wire signed [2:0] out;

  // the circuit under test
   sdiv3 s(out, in);  
    
   initial begin               // initial = run at beginning of simulation
                               // begin/end = associate block with initial
      
      $dumpfile("test.vcd");  // name of dump file to create
      $dumpvars(0, test);     // record all signals of module "test" and sub-modules
                              // remember to change "test" to the correct
                              // module name when writing your own test benches
        
      // test all input combinations
      in = 0; #10;
      in = 1; #10;
      in = 2; #10;
      in = 3; #10;
      in = 4; #10;
      in = 5; #10;
      in = 6; #10;
      in = 7; #10;
      in = 8; #10;
      in = 9; #10;
      in = 10; #10;
      in = 11; #10;
      in = 12; #10;
      in = 13; #10;
      in = 14; #10;
      in = 15; #10;
      
      $finish;        // end the simulation
   end                      
   
   initial begin
     $display("inputs = in  outputs = out");
     $monitor("inputs = %d  outputs = %d   time = %2t", in, out, $time);
   end
endmodule // test

cs233/exam/exam1/p2/test.vcd
$date
	Mon Feb  5 20:49:48 2018
$end
$version
	Icarus Verilog
$end
$timescale
	1s
$end
$scope module test $end
$var wire 3 ! out [2:0] $end
$var reg 4 " in [3:0] $end
$scope module s $end
$var wire 4 # in [3:0] $end
$var wire 3 $ out [2:0] $end
$upscope $end
$upscope $end
$enddefinitions $end
#0
$dumpvars
b0 $
b0 #
b0 "
b0 !
$end
#10
b1 "
b1 #
#20
b10 "
b10 #
#30
b1 !
b1 $
b11 "
b11 #
#40
b100 "
b100 #
#50
b101 "
b101 #
#60
b10 !
b10 $
b110 "
b110 #
#70
b111 "
b111 #
#80
b110 !
b110 $
b1000 "
b1000 #
#90
b1001 "
b1001 #
#100
b1010 "
b1010 #
#110
b111 !
b111 $
b1011 "
b1011 #
#120
b1100 "
b1100 #
#130
b1101 "
b1101 #
#140
b0 !
b0 $
b1110 "
b1110 #
#150
b1111 "
b1111 #
